{
    "version": 3,
    "cmakeMinimumRequired": {
        "major": 4
    },
    "configurePresets": [
        {
            "name": "windows-base",
            "hidden": true,
            "generator": "Ninja",
            "binaryDir": "${sourceDir}/build",
            "installDir": "${sourceDir}/build/install/${presetName}",
            "cacheVariables": {
                "CMAKE_C_COMPILER": "cl.exe",
                "CMAKE_CXX_COMPILER": "cl.exe"
            },
            "condition": {
                "type": "equals",
                "lhs": "${hostSystemName}",
                "rhs": "Windows"
            }
        },
        {
            "name": "x64-debug",
            "displayName": "x64 Debug",
            "inherits": "windows-base",
            "architecture": {
                "value": "x64",
                "strategy": "external"
            },
            "cacheVariables": {
                "CMAKE_BUILD_TYPE": "Debug",
                "CMAKE_CXX_FLAGS_DEBUG": "/fp:fast /DDEBUG /DTRACY_ENABLE"
            }
        },
        {
            "name": "x64-deploy",
            "displayName": "x64 Deploy",
            "inherits": "x64-debug",
            "cacheVariables": {
                "CMAKE_BUILD_TYPE": "Release",
                "CMAKE_C_FLAGS_RELEASE": "/fp:fast /O2 /Zi",
                "CMAKE_CXX_FLAGS_RELEASE": "/fp:fast /O2 /Zi /DINTEL_NO_ITTNOTIFY_API /DDEPLOY"
            }
        },
        {
            "name": "x64-release",
            "displayName": "x64 Release (with debug symbols)",
            "inherits": "x64-debug",
            "cacheVariables": {
                "CMAKE_BUILD_TYPE": "Release",
                "CMAKE_C_FLAGS_RELEASE": "/fp:fast /Ob3 /O2 /Zi",
                "CMAKE_CXX_FLAGS_RELEASE": "/fp:fast /Ob3 /O2 /Zi /DTRACY_ENABLE",
                "CMAKE_EXE_LINKER_FLAGS": "/DEBUG",
                "CMAKE_SHARED_LINKER_FLAGS": "/DEBUG"
            }
        },
        {
            "name": "x86-debug",
            "displayName": "x86 Debug",
            "inherits": "windows-base",
            "architecture": {
                "value": "x86",
                "strategy": "external"
            },
            "cacheVariables": {
                "CMAKE_BUILD_TYPE": "Debug",
                "CMAKE_CXX_FLAGS_DEBUG": "/fp:fast /DDEBUG /DTRACY_ENABLE"
            }
        },
        {
            "name": "x86-deploy",
            "displayName": "x86 Deploy",
            "inherits": "x86-eploy",
            "displayName": "x86 Deploy",
            "inherits": "x86-debug",
            "cacheVariables": {
                "CMAKE_BUILD_TYPE": "Release",
                "CMAKE_C_FLAGS_RELEASE": "/fp:fast /Ob3 /O2 /Zi",
                "CMAKE_CXX_FLAGS_RELEASE": "/fp:fast /Ob3 /O2 /Zi /DINTEL_NO_ITTNOTIFY_API /DDEPLOY"
            }
        },
        {
            "name": "x86-release",
            "displayName": "x86 Release (with debug symbols)",
            "inherits": "x86-debug",
            "cacheVariables": {
                "CMAKE_BUILD_TYPE": "Release",
                "CMAKE_C_FLAGS_RELEASE": "/fp:fast /Ob3 /O2 /Zi",
                "CMAKE_CXX_FLAGS_RELEASE": "/fp:fast /Ob3 /O2 /Zi /DTRACY_ENABLE",
                "CMAKE_EXE_LINKER_FLAGS": "/DEBUG",
                "CMAKE_SHARED_LINKER_FLAGS": "/DEBUG"
            }
        },
        {
            "name": "linux-debug",
            "displayName": "Linux Debug",
            "generator": "Ninja",
            "binaryDir": "${sourceDir}/build/${presetName}",
            "installDir": "${sourceDir}/build/install/${presetName}",
            "cacheVariables": {
                "CMAKE_BUILD_TYPE": "Debug",
                "CMAKE_C_COMPILER": "gcc-13",
                "CMAKE_CXX_COMPILER": "g++-13"
            },
            "condition": {
                "type": "equals",
                "lhs": "${hostSystemName}",
                "rhs": "Linux"
            },
            "vendor": {
                "microsoft.com/VisualStudioRemoteSettings/CMake/1.0": {
                    "sourceDir": "$env{HOME}/.vs/$ms{projectDirName}"
                }
            }
        },
        {
            "name": "macos-debug",
            "displayName": "macOS Debug",
            "generator": "Ninja",
            "binaryDir": "${sourceDir}/out/build/${presetName}",
            "installDir": "${sourceDir}/out/install/${presetName}",
            "cacheVariables": {
                "CMAKE_BUILD_TYPE": "Debug"
            },
            "condition": {
                "type": "equals",
                "lhs": "${hostSystemName}",
                "rhs": "Darwin"
            },
            "vendor": {
                "microsoft.com/VisualStudioRemoteSettings/CMake/1.0": {
                    "sourceDir": "$env{HOME}/.vs/$ms{projectDirName}"
                }
            }
        }
    ]
}